fastapi_cli/__init__.py
fastapi_cli/__main__.py
fastapi_cli/config.py
fastapi_cli/constants.py
fastapi_cli/context.py
fastapi_cli/generator.py
fastapi_cli/helpers.py
fastapi_cli/main.py
fastapi_cli/templates/__init__.py
fastapi_cli/templates/app/__init__.py
fastapi_cli/templates/app/cookiecutter.json
fastapi_cli/templates/app/hooks/post_gen_project.py
fastapi_cli/templates/project/__init__.py
fastapi_cli/templates/project/cookiecutter.json
fastapi_cli/templates/project/hooks/post_gen_project.py
fastapi_cli/templates/project/{{ cookiecutter.folder_name }}/Dockerfile
fastapi_cli/templates/project/{{ cookiecutter.folder_name }}/LICENSE
fastapi_cli/templates/project/{{ cookiecutter.folder_name }}/README.md
fastapi_cli/templates/project/{{ cookiecutter.folder_name }}/docker-compose.yaml
fastapi_cli/templates/project/{{ cookiecutter.folder_name }}/pyproject.toml
fastapi_cli/templates/project/{{ cookiecutter.folder_name }}/requirements.txt
fastapi_cli/templates/project/{{ cookiecutter.folder_name }}/setup.cfg
fastapi_cli/templates/project/{{ cookiecutter.folder_name }}/{{ cookiecutter.env }}
fastapi_cli/templates/project/{{ cookiecutter.folder_name }}/{{ cookiecutter.gitignore }}
fastapi_cli_service-1.0.1.dist-info/LICENSE
fastapi_cli_service-1.0.1.dist-info/METADATA
fastapi_cli_service-1.0.1.dist-info/WHEEL
fastapi_cli_service-1.0.1.dist-info/entry_points.txt
fastapi_cli_service-1.0.1.dist-info/top_level.txt
fastapi_cli_service-1.0.1.dist-info/RECORD
